sklearn_nature_inspired_algorithms/__init__.py
sklearn_nature_inspired_algorithms/helpers/__init__.py
sklearn_nature_inspired_algorithms/helpers/score_by_generation_lineplot.py
sklearn_nature_inspired_algorithms/helpers/score_by_generation_violinplot.py
sklearn_nature_inspired_algorithms/model_selection/__init__.py
sklearn_nature_inspired_algorithms/model_selection/_param_grid.py
sklearn_nature_inspired_algorithms/model_selection/_parameter_search.py
sklearn_nature_inspired_algorithms/model_selection/_stagnation_stopping_task.py
sklearn_nature_inspired_algorithms/model_selection/nature_inspired_search_cv.py
sklearn_nature_inspired_algorithms-0.12.0.dist-info/LICENSE
sklearn_nature_inspired_algorithms-0.12.0.dist-info/METADATA
sklearn_nature_inspired_algorithms-0.12.0.dist-info/WHEEL
sklearn_nature_inspired_algorithms-0.12.0.dist-info/RECORD
