Metadata-Version: 2.1
Name: sklearn-nature-inspired-algorithms
Version: 0.12.0
Summary: Search using nature inspired algorithms over specified parameter values for an sklearn estimator.
Home-page: https://github.com/timzatko/Sklearn-Nature-Inspired-Algorithms
License: MIT
Keywords: sklearn,scikit-learn,nature-inspired-algorithms,hyper-parameter-tuning
Author: Timotej Zatko
Author-email: timi.zatko@gmail.com
Requires-Python: >=3.8.1,<=3.12
Classifier: License :: OSI Approved :: MIT License
Classifier: Programming Language :: Python :: 3
Classifier: Programming Language :: Python :: 3.9
Classifier: Programming Language :: Python :: 3.10
Classifier: Programming Language :: Python :: 3.11
Requires-Dist: matplotlib (>=3.5,<4.0.0)
Requires-Dist: niapy (>=2.0)
Requires-Dist: numpy (>=1.22,<2.0.0)
Requires-Dist: pandas (>=1.4,<2.0.0)
Requires-Dist: scikit-learn (>=1.0.2)
Requires-Dist: scipy (>=1.7.3)
Requires-Dist: seaborn (>=0.11,<1.0.0)
Requires-Dist: toml (>=0.10,<1.0.0)
Project-URL: Repository, https://github.com/timzatko/Sklearn-Nature-Inspired-Algorithms
